catdns/__init__.py
catdns/async_session.py
catdns/asyncio.py
catdns/session.py
catdns/types.py
catdns-2.0.dist-info/LICENSE
catdns-2.0.dist-info/METADATA
catdns-2.0.dist-info/WHEEL
catdns-2.0.dist-info/top_level.txt
catdns-2.0.dist-info/RECORD
